onceml/__init__.py
onceml/data_loader.py
onceml/onceml.py
onceml/sync.py
onceml-0.1.2.dist-info/entry_points.txt
onceml-0.1.2.dist-info/WHEEL
onceml-0.1.2.dist-info/METADATA
onceml-0.1.2.dist-info/RECORD
